ai_judge/__init__.py
ai_judge-0.0.1.dist-info/METADATA
ai_judge-0.0.1.dist-info/WHEEL
ai_judge-0.0.1.dist-info/RECORD
